win64pyinstaller/__init__.py
win64pyinstaller-0.1.dist-info/LICENSE
win64pyinstaller-0.1.dist-info/METADATA
win64pyinstaller-0.1.dist-info/WHEEL
win64pyinstaller-0.1.dist-info/top_level.txt
win64pyinstaller-0.1.dist-info/RECORD
