Metadata-Version: 2.1
Name: win64pyinstaller
Version: 0.1
Summary: A package for windows which installes additional and small components for modules/projects
Home-page: https://github.com/Pranav578/win64installer
Author: Pranav
Author-email: pranavbairy2@gmail.com
License: UNKNOWN
Project-URL: Bug Tracker, https://github.com/Pranav578/win64py/issues
Keywords: win64pyinstall,pywin64installer,pysetupinstaller,wpi64
Platform: UNKNOWN
Classifier: Programming Language :: Python :: 3
Classifier: License :: OSI Approved :: MIT License
Classifier: Operating System :: OS Independent
Requires-Python: >=3.5
License-File: LICENSE
